mscore/__init__.py
mscore/fuzzy.py
mscore/instruments.py
mscore/test.py
mscore/res/score.mscx
mscore/res/score.mscz
mscore/scripts/__init__.py
mscore/scripts/ms_cleanup.py
mscore/scripts/ms_colorize.py
mscore/scripts/ms_concatenate.py
mscore/scripts/ms_copy_instrument.py
mscore/scripts/ms_create_template.py
mscore/scripts/ms_info.py
mscore/scripts/ms_port_partition.py
mscore3-1.17.1.dist-info/entry_points.txt
mscore3-1.17.1.dist-info/LICENSE
mscore3-1.17.1.dist-info/WHEEL
mscore3-1.17.1.dist-info/METADATA
mscore3-1.17.1.dist-info/RECORD
