Metadata-Version: 2.1
Name: mscore3
Version: 1.17.1
Summary: A python library for opening/inspecting/modifying MuseScore3 files.
Author-email: Leon Dionne <ldionne@dridesign.sh.cn>
Classifier: Development Status :: 3 - Alpha
Classifier: License :: OSI Approved :: GNU General Public License v3 or later (GPLv3+)
Classifier: Intended Audience :: Developers
Classifier: Programming Language :: Python
Classifier: Programming Language :: Python :: 3.10
Classifier: Topic :: Multimedia :: Sound/Audio
Classifier: Topic :: Multimedia :: Sound/Audio :: Editors
Classifier: Topic :: Multimedia :: Sound/Audio :: MIDI
Requires-Dist: sf2utils
Requires-Dist: appdirs
Requires-Dist: console_quiet
Requires-Dist: node_soso >= 1.3.0
Project-URL: Home, https://github.com/Zen-Master-SoSo/mscore
